redis_allocator/__init__.py
redis_allocator/_version.py
redis_allocator/allocator.py
redis_allocator/lock.py
redis_allocator/task_queue.py
redis_allocator-0.6.0.dist-info/licenses/LICENSE
tests/__init__.py
tests/conftest.py
tests/test_allocator.py
tests/test_lock.py
tests/test_task_queue.py
redis_allocator-0.6.0.dist-info/METADATA
redis_allocator-0.6.0.dist-info/WHEEL
redis_allocator-0.6.0.dist-info/top_level.txt
redis_allocator-0.6.0.dist-info/RECORD
