Metadata-Version: 2.4
Name: redis-allocator
Version: 0.6.0
Summary: Redis-based resource allocation system.
Home-page: https://github.com/invoker-bot/RedisAllocator-python
Author: Invoker Bot
Author-email: invoker-bot@outlook.com
License: MIT
Classifier: Development Status :: 4 - Beta
Classifier: Intended Audience :: Developers
Classifier: Programming Language :: Python :: 3.9
Classifier: License :: OSI Approved :: MIT License
Classifier: Operating System :: OS Independent
Classifier: Topic :: Software Development :: Libraries :: Python Modules
Requires-Python: >=3.10
License-File: LICENSE
Requires-Dist: redis>=5.0.0
Requires-Dist: cachetools>=5.3.2
Provides-Extra: test
Requires-Dist: pytest>=7.4.3; extra == "test"
Requires-Dist: pytest-cov>=4.1.0; extra == "test"
Requires-Dist: pytest-mock>=3.12.0; extra == "test"
Requires-Dist: fakeredis[lua]>=2.20.1; extra == "test"
Requires-Dist: flake8>=6.1.0; extra == "test"
Requires-Dist: freezegun>=1.4.0; extra == "test"
Provides-Extra: docs
Requires-Dist: sphinx>=7.0.0; extra == "docs"
Requires-Dist: sphinx-rtd-theme>=1.3.0; extra == "docs"
Requires-Dist: sphinx-git>=11.0.0; extra == "docs"
Requires-Dist: sphinxcontrib-mermaid>=0.7.1; extra == "docs"
Provides-Extra: dev
Requires-Dist: pytest>=7.4.3; extra == "dev"
Requires-Dist: pytest-cov>=4.1.0; extra == "dev"
Requires-Dist: pytest-mock>=3.12.0; extra == "dev"
Requires-Dist: fakeredis[lua]>=2.20.1; extra == "dev"
Requires-Dist: flake8>=6.1.0; extra == "dev"
Requires-Dist: freezegun>=1.4.0; extra == "dev"
Requires-Dist: sphinx>=7.0.0; extra == "dev"
Requires-Dist: sphinx-rtd-theme>=1.3.0; extra == "dev"
Requires-Dist: sphinx-git>=11.0.0; extra == "dev"
Requires-Dist: sphinxcontrib-mermaid>=0.7.1; extra == "dev"
Dynamic: author
Dynamic: author-email
Dynamic: classifier
Dynamic: description
Dynamic: description-content-type
Dynamic: home-page
Dynamic: license
Dynamic: license-file
Dynamic: provides-extra
Dynamic: requires-dist
Dynamic: requires-python
Dynamic: summary
